toxasup/__init__.py
toxasup/classes.py
toxasup/toxasup.py
Toxa4_Sup-0.0.2.dist-info/LICENSE
Toxa4_Sup-0.0.2.dist-info/METADATA
Toxa4_Sup-0.0.2.dist-info/WHEEL
Toxa4_Sup-0.0.2.dist-info/top_level.txt
Toxa4_Sup-0.0.2.dist-info/RECORD
