Metadata-Version: 2.1
Name: Toxa4-Sup
Version: 0.0.2
Summary: This is my 1st project 
Home-page: https://github.com/dimaterig0404
Author: Dima Zyryanov
Author-email: dima.terig02@gmail.com
License: UNKNOWN
Platform: UNKNOWN
Classifier: Programming Language :: Python :: 3.8
Classifier: License :: OSI Approved :: MIT License
Classifier: Operating System :: OS Independent
Requires-Python: >=3.5
Requires-Dist: requests (<=2.21.0)
Requires-Dist: pyowm (<=3.1.1)
Requires-Dist: opencv-python
